minpower/__init__.py
minpower/bidding.py
minpower/commonscripts.py
minpower/config.py
minpower/generators.py
minpower/get_data.py
minpower/optimization.py
minpower/powersystems.py
minpower/results.py
minpower/schedule.py
minpower/solve.py
minpower/standalone.py
minpower/stochastic.py
minpower/configuration/__init__.py
minpower/configuration/minpower.cfg
minpower/experiments/__init__.py
minpower/experiments/ed_sweep.py
minpower/experiments/formulation_speed_check.py
minpower/experiments/get_initial_dispatch.py
minpower/experiments/scheduler_minpower.py
minpower/tests/__init__.py
minpower/tests/memory_leak_check.py
minpower/tests/run_all_cases.py
minpower/tests/test_bidding.py
minpower/tests/test_data_in.py
minpower/tests/test_duals.py
minpower/tests/test_generators.py
minpower/tests/test_integration.py
minpower/tests/test_opf.py
minpower/tests/test_results.py
minpower/tests/test_solvers.py
minpower/tests/test_stochastic.py
minpower/tests/test_uc.py
minpower/tests/test_utils.py
minpower/tests/deterministic_perfect_difference/generators.csv
minpower/tests/deterministic_perfect_difference/loads.csv
minpower/tests/deterministic_perfect_difference/wind_forecast.csv
minpower/tests/deterministic_perfect_difference/wind_observed.csv
minpower/tests/ed/dispatch.csv
minpower/tests/ed/generators.csv
minpower/tests/ed/loads.csv
minpower/tests/ed-WW-3-7/dispatch.csv
minpower/tests/ed-WW-3-7/generators.csv
minpower/tests/ed-WW-3-7/loads.csv
minpower/tests/ed-custom-bidding-points/bid-points-cheap.csv
minpower/tests/ed-custom-bidding-points/bid-points-expensive.csv
minpower/tests/ed-custom-bidding-points/generators.csv
minpower/tests/ed-custom-bidding-points/loads.csv
minpower/tests/ed-gen-Pmax/generators.csv
minpower/tests/ed-gen-Pmax/loads.csv
minpower/tests/ed-gen-Pmin/generators.csv
minpower/tests/ed-gen-Pmin/loads.csv
minpower/tests/expected_observed_cost/generators.csv
minpower/tests/expected_observed_cost/loads.csv
minpower/tests/expected_observed_cost/wind_forecast.csv
minpower-5.0.1.dist-info/METADATA
minpower-5.0.1.dist-info/WHEEL
minpower-5.0.1.dist-info/entry_points.txt
minpower-5.0.1.dist-info/top_level.txt
minpower-5.0.1.dist-info/RECORD
